{
  "cli": {
    "version": ">= 16.0.1",
    "appVersionSource": "remote"
  },
  "build": {
    "development": {
      "developmentClient": true,
      "distribution": "internal",
      "env": {
        "EXPO_PUBLIC_SUPABASE_URL": "https://luvgzsvchwvuhlfmgmsq.supabase.co",
        "EXPO_PUBLIC_SUPABASE_ANON_KEY": "sb_publishable_aqEEWvFTkKwmxXtkDxdMxQ_u4bfpyqG"
      }
    },
    "preview": {
      "android": {
        "buildType": "apk"
      },
      "distribution": "internal",
      "env": {
        "EXPO_PUBLIC_SUPABASE_URL": "https://luvgzsvchwvuhlfmgmsq.supabase.co",
        "EXPO_PUBLIC_SUPABASE_ANON_KEY": "sb_publishable_aqEEWvFTkKwmxXtkDxdMxQ_u4bfpyqG"
      }
    },
    "production": {
      "autoIncrement": true,
      "env": {
        "EXPO_PUBLIC_SUPABASE_URL": "https://luvgzsvchwvuhlfmgmsq.supabase.co",
        "EXPO_PUBLIC_SUPABASE_ANON_KEY": "sb_publishable_aqEEWvFTkKwmxXtkDxdMxQ_u4bfpyqG"
      }
    }
  },
  "submit": {
    "production": {}
  }
}
